wolfpy/__init__.py
wolfpy/__main__.py
wolfpy/app.py
wolfpy/admin/__init__.py
wolfpy/admin/static/admin.css
wolfpy/cli/__init__.py
wolfpy/cli/main.py
wolfpy/cli/migrations.py
wolfpy/core/__init__.py
wolfpy/core/admin.py
wolfpy/core/advanced_auth.py
wolfpy/core/advanced_database.py
wolfpy/core/advanced_middleware.py
wolfpy/core/api.py
wolfpy/core/api_decorators.py
wolfpy/core/asgi.py
wolfpy/core/auth.py
wolfpy/core/auth_routes.py
wolfpy/core/cache.py
wolfpy/core/database.py
wolfpy/core/docs.py
wolfpy/core/error_handling.py
wolfpy/core/middleware.py
wolfpy/core/middleware_enhanced.py
wolfpy/core/migrations.py
wolfpy/core/performance.py
wolfpy/core/plugins.py
wolfpy/core/realtime.py
wolfpy/core/request.py
wolfpy/core/response.py
wolfpy/core/router.py
wolfpy/core/security.py
wolfpy/core/security_enhanced.py
wolfpy/core/session.py
wolfpy/core/template_engine.py
wolfpy/core/websocket.py
wolfpy/core/adapters/__init__.py
wolfpy/core/adapters/base.py
wolfpy/core/adapters/mongodb.py
wolfpy/core/adapters/mysql.py
wolfpy/core/adapters/postgresql.py
wolfpy/core/adapters/redis.py
wolfpy/core/adapters/sqlite.py
wolfpy/static/style.css
wolfpy/templates/base.html
wolfpy/templates/auth/base.html
wolfpy/templates/auth/login.html
wolfpy/templates/auth/profile.html
wolfpy/templates/auth/register.html
wolfpy/templates/errors/404.html
wolfpy/templates/errors/422.html
wolfpy/templates/errors/500.html
wolfpy/templates/errors/base_error.html
wolfpy/testing/enhanced_test_client.py
wolfpy-0.1.1.dist-info/METADATA
wolfpy-0.1.1.dist-info/WHEEL
wolfpy-0.1.1.dist-info/entry_points.txt
wolfpy-0.1.1.dist-info/licenses/LICENSE
wolfpy-0.1.1.dist-info/RECORD
