Metadata-Version: 2.4
Name: wolfpy
Version: 0.1.1
Summary: A modular Python web framework built from scratch using AI
Project-URL: Homepage, https://github.com/manish12ys/wolfpy
Project-URL: Repository, https://github.com/manish12ys/wolfpy
Project-URL: Documentation, https://wolfpy.readthedocs.io
Project-URL: Bug Tracker, https://github.com/manish12ys/wolfpy/issues
Author-email: Manish <manishchowdary2006@gmail.com>
License-Expression: MIT
License-File: LICENSE
Classifier: Development Status :: 3 - Alpha
Classifier: Intended Audience :: Developers
Classifier: License :: OSI Approved :: MIT License
Classifier: Operating System :: OS Independent
Classifier: Programming Language :: Python :: 3
Classifier: Programming Language :: Python :: 3.9
Classifier: Programming Language :: Python :: 3.10
Classifier: Programming Language :: Python :: 3.11
Classifier: Programming Language :: Python :: 3.12
Classifier: Topic :: Internet :: WWW/HTTP :: WSGI
Classifier: Topic :: Software Development :: Libraries :: Python Modules
Requires-Python: >=3.9
Requires-Dist: bcrypt>=4.0.0
Requires-Dist: jinja2>=3.1.0
Requires-Dist: mako>=1.2.0
Requires-Dist: markdown>=3.4.0
Requires-Dist: markupsafe>=2.1.0
Requires-Dist: pygments>=2.15.0
Provides-Extra: all-databases
Requires-Dist: mysql-connector-python>=8.0.0; extra == 'all-databases'
Requires-Dist: psycopg2-binary>=2.9.0; extra == 'all-databases'
Requires-Dist: pymongo>=4.0.0; extra == 'all-databases'
Requires-Dist: redis>=4.0.0; extra == 'all-databases'
Provides-Extra: deployment
Requires-Dist: docker>=6.0.0; extra == 'deployment'
Requires-Dist: python-dotenv>=1.0.0; extra == 'deployment'
Provides-Extra: dev
Requires-Dist: black>=23.0.0; extra == 'dev'
Requires-Dist: flake8>=6.0.0; extra == 'dev'
Requires-Dist: mypy>=1.0.0; extra == 'dev'
Requires-Dist: pytest-asyncio>=0.21.0; extra == 'dev'
Requires-Dist: pytest-cov>=4.0.0; extra == 'dev'
Requires-Dist: pytest>=7.0.0; extra == 'dev'
Provides-Extra: mongodb
Requires-Dist: pymongo>=4.0.0; extra == 'mongodb'
Provides-Extra: mysql
Requires-Dist: mysql-connector-python>=8.0.0; extra == 'mysql'
Provides-Extra: postgresql
Requires-Dist: psycopg2-binary>=2.9.0; extra == 'postgresql'
Provides-Extra: production
Requires-Dist: gevent>=23.0.0; extra == 'production'
Requires-Dist: gunicorn>=21.0.0; extra == 'production'
Requires-Dist: uvicorn[standard]>=0.24.0; extra == 'production'
Provides-Extra: redis
Requires-Dist: redis>=4.0.0; extra == 'redis'
